adafruit_circuitpython_neokey-1.1.7.dist-info/licenses/LICENSE
adafruit_neokey/__init__.py
adafruit_neokey/neokey1x4.py
adafruit_circuitpython_neokey-1.1.7.dist-info/METADATA
adafruit_circuitpython_neokey-1.1.7.dist-info/WHEEL
adafruit_circuitpython_neokey-1.1.7.dist-info/top_level.txt
adafruit_circuitpython_neokey-1.1.7.dist-info/RECORD
